tinytinyscraper/__init__.py
tinytinyscraper/scraper.py
tinytinyscraper-0.1.1.dist-info/licenses/LICENSE
tinytinyscraper-0.1.1.dist-info/METADATA
tinytinyscraper-0.1.1.dist-info/WHEEL
tinytinyscraper-0.1.1.dist-info/top_level.txt
tinytinyscraper-0.1.1.dist-info/RECORD
