Metadata-Version: 2.4
Name: tinytinyscraper
Version: 0.1.1
Summary: A Python library that scrapes URLs and returns their contents. Special handling for YouTube URLs to extract transcripts and PDF files to extract text. Built with BeautifulSoup, Requests, YouTube-Transcript-API, and PyPDF.
Author-email: Justin Irabor <justin@holeyfox.co>
Maintainer-email: Justin Irabor <justin@holeyfox.co>
License: MIT
Project-URL: Homepage, https://github.com/vunderkind/tinytinyscraper
Project-URL: Repository, https://github.com/vunderkind/tinytinyscraper
Keywords: scraper,youtube,transcript,web-scraping,url,pdf,pdf-extraction
Classifier: Development Status :: 3 - Alpha
Classifier: Intended Audience :: Developers
Classifier: License :: OSI Approved :: MIT License
Classifier: Programming Language :: Python :: 3
Classifier: Programming Language :: Python :: 3.9
Classifier: Programming Language :: Python :: 3.10
Classifier: Programming Language :: Python :: 3.11
Classifier: Programming Language :: Python :: 3.12
Requires-Python: >=3.9
License-File: LICENSE
Requires-Dist: requests>=2.32.0
Requires-Dist: beautifulsoup4>=4.12.0
Requires-Dist: youtube-transcript-api>=0.6.0
Requires-Dist: lxml>=4.9.0
Requires-Dist: pypdf>=3.0.0
Provides-Extra: dev
Requires-Dist: pytest>=7.0.0; extra == "dev"
Requires-Dist: black>=23.0.0; extra == "dev"
Requires-Dist: flake8>=6.0.0; extra == "dev"
Dynamic: license-file
